{
  "url": "https://api.github.com/repos/LeoLun/willow/releases/328704660",
  "assets_url": "https://api.github.com/repos/LeoLun/willow/releases/328704660/assets",
  "upload_url": "https://uploads.github.com/repos/LeoLun/willow/releases/328704660/assets{?name,label}",
  "html_url": "https://github.com/LeoLun/willow/releases/tag/v0.0.2",
  "id": 328704660,
  "author": {
    "login": "github-actions[bot]",
    "id": 41898282,
    "node_id": "MDM6Qm90NDE4OTgyODI=",
    "avatar_url": "https://avatars.githubusercontent.com/in/15368?v=4",
    "gravatar_id": "",
    "url": "https://api.github.com/users/github-actions%5Bbot%5D",
    "html_url": "https://github.com/apps/github-actions",
    "followers_url": "https://api.github.com/users/github-actions%5Bbot%5D/followers",
    "following_url": "https://api.github.com/users/github-actions%5Bbot%5D/following{/other_user}",
    "gists_url": "https://api.github.com/users/github-actions%5Bbot%5D/gists{/gist_id}",
    "starred_url": "https://api.github.com/users/github-actions%5Bbot%5D/starred{/owner}{/repo}",
    "subscriptions_url": "https://api.github.com/users/github-actions%5Bbot%5D/subscriptions",
    "organizations_url": "https://api.github.com/users/github-actions%5Bbot%5D/orgs",
    "repos_url": "https://api.github.com/users/github-actions%5Bbot%5D/repos",
    "events_url": "https://api.github.com/users/github-actions%5Bbot%5D/events{/privacy}",
    "received_events_url": "https://api.github.com/users/github-actions%5Bbot%5D/received_events",
    "type": "Bot",
    "user_view_type": "public",
    "site_admin": false
  },
  "node_id": "RE_kwDOOgHXD84Tl6KU",
  "tag_name": "v0.0.2",
  "target_commitish": "main",
  "name": "Release v0.0.2",
  "draft": false,
  "immutable": false,
  "prerelease": false,
  "created_at": "2026-05-24T04:30:44Z",
  "updated_at": "2026-05-25T07:24:35Z",
  "published_at": "2026-05-25T07:24:35Z",
  "assets": [
    {
      "url": "https://api.github.com/repos/LeoLun/willow/releases/assets/429149112",
      "id": 429149112,
      "node_id": "RA_kwDOOgHXD84ZlEu4",
      "name": "app.asar",
      "label": "",
      "uploader": {
        "login": "github-actions[bot]",
        "id": 41898282,
        "node_id": "MDM6Qm90NDE4OTgyODI=",
        "avatar_url": "https://avatars.githubusercontent.com/in/15368?v=4",
        "gravatar_id": "",
        "url": "https://api.github.com/users/github-actions%5Bbot%5D",
        "html_url": "https://github.com/apps/github-actions",
        "followers_url": "https://api.github.com/users/github-actions%5Bbot%5D/followers",
        "following_url": "https://api.github.com/users/github-actions%5Bbot%5D/following{/other_user}",
        "gists_url": "https://api.github.com/users/github-actions%5Bbot%5D/gists{/gist_id}",
        "starred_url": "https://api.github.com/users/github-actions%5Bbot%5D/starred{/owner}{/repo}",
        "subscriptions_url": "https://api.github.com/users/github-actions%5Bbot%5D/subscriptions",
        "organizations_url": "https://api.github.com/users/github-actions%5Bbot%5D/orgs",
        "repos_url": "https://api.github.com/users/github-actions%5Bbot%5D/repos",
        "events_url": "https://api.github.com/users/github-actions%5Bbot%5D/events{/privacy}",
        "received_events_url": "https://api.github.com/users/github-actions%5Bbot%5D/received_events",
        "type": "Bot",
        "user_view_type": "public",
        "site_admin": false
      },
      "content_type": "application/octet-stream",
      "state": "uploaded",
      "size": 16822622,
      "digest": "sha256:d71de6391d4d2ee018381d1f5a0c0d610ac26fdd3da343d5263abc2cd1ebffbb",
      "download_count": 0,
      "created_at": "2026-05-25T07:24:27Z",
      "updated_at": "2026-05-25T07:24:28Z",
      "browser_download_url": "https://github.com/LeoLun/willow/releases/download/v0.0.2/app.asar"
    },
    {
      "url": "https://api.github.com/repos/LeoLun/willow/releases/assets/429149110",
      "id": 429149110,
      "node_id": "RA_kwDOOgHXD84ZlEu2",
      "name": "Willow-Work-v0.0.2-arm64.dmg",
      "label": "",
      "uploader": {
        "login": "github-actions[bot]",
        "id": 41898282,
        "node_id": "MDM6Qm90NDE4OTgyODI=",
        "avatar_url": "https://avatars.githubusercontent.com/in/15368?v=4",
        "gravatar_id": "",
        "url": "https://api.github.com/users/github-actions%5Bbot%5D",
        "html_url": "https://github.com/apps/github-actions",
        "followers_url": "https://api.github.com/users/github-actions%5Bbot%5D/followers",
        "following_url": "https://api.github.com/users/github-actions%5Bbot%5D/following{/other_user}",
        "gists_url": "https://api.github.com/users/github-actions%5Bbot%5D/gists{/gist_id}",
        "starred_url": "https://api.github.com/users/github-actions%5Bbot%5D/starred{/owner}{/repo}",
        "subscriptions_url": "https://api.github.com/users/github-actions%5Bbot%5D/subscriptions",
        "organizations_url": "https://api.github.com/users/github-actions%5Bbot%5D/orgs",
        "repos_url": "https://api.github.com/users/github-actions%5Bbot%5D/repos",
        "events_url": "https://api.github.com/users/github-actions%5Bbot%5D/events{/privacy}",
        "received_events_url": "https://api.github.com/users/github-actions%5Bbot%5D/received_events",
        "type": "Bot",
        "user_view_type": "public",
        "site_admin": false
      },
      "content_type": "application/x-apple-diskimage",
      "state": "uploaded",
      "size": 105117851,
      "digest": "sha256:0e2a1a710df616b4369d93eecb5ad5ac74802cee993b19e46d0d82bc0a4e45d4",
      "download_count": 0,
      "created_at": "2026-05-25T07:24:27Z",
      "updated_at": "2026-05-25T07:24:33Z",
      "browser_download_url": "https://github.com/LeoLun/willow/releases/download/v0.0.2/Willow-Work-v0.0.2-arm64.dmg"
    },
    {
      "url": "https://api.github.com/repos/LeoLun/willow/releases/assets/429149113",
      "id": 429149113,
      "node_id": "RA_kwDOOgHXD84ZlEu5",
      "name": "Willow-Work-v0.0.2-x64.dmg",
      "label": "",
      "uploader": {
        "login": "github-actions[bot]",
        "id": 41898282,
        "node_id": "MDM6Qm90NDE4OTgyODI=",
        "avatar_url": "https://avatars.githubusercontent.com/in/15368?v=4",
        "gravatar_id": "",
        "url": "https://api.github.com/users/github-actions%5Bbot%5D",
        "html_url": "https://github.com/apps/github-actions",
        "followers_url": "https://api.github.com/users/github-actions%5Bbot%5D/followers",
        "following_url": "https://api.github.com/users/github-actions%5Bbot%5D/following{/other_user}",
        "gists_url": "https://api.github.com/users/github-actions%5Bbot%5D/gists{/gist_id}",
        "starred_url": "https://api.github.com/users/github-actions%5Bbot%5D/starred{/owner}{/repo}",
        "subscriptions_url": "https://api.github.com/users/github-actions%5Bbot%5D/subscriptions",
        "organizations_url": "https://api.github.com/users/github-actions%5Bbot%5D/orgs",
        "repos_url": "https://api.github.com/users/github-actions%5Bbot%5D/repos",
        "events_url": "https://api.github.com/users/github-actions%5Bbot%5D/events{/privacy}",
        "received_events_url": "https://api.github.com/users/github-actions%5Bbot%5D/received_events",
        "type": "Bot",
        "user_view_type": "public",
        "site_admin": false
      },
      "content_type": "application/x-apple-diskimage",
      "state": "uploaded",
      "size": 115740233,
      "digest": "sha256:fc78be6fc3d8e824dcb8334afa5a7f7e4a33beda17cc0276935c28b4707eb93d",
      "download_count": 0,
      "created_at": "2026-05-25T07:24:27Z",
      "updated_at": "2026-05-25T07:24:34Z",
      "browser_download_url": "https://github.com/LeoLun/willow/releases/download/v0.0.2/Willow-Work-v0.0.2-x64.dmg"
    },
    {
      "url": "https://api.github.com/repos/LeoLun/willow/releases/assets/429149111",
      "id": 429149111,
      "node_id": "RA_kwDOOgHXD84ZlEu3",
      "name": "Willow.Work-darwin-arm64-0.0.2.zip",
      "label": "Willow Work-darwin-arm64-0.0.2.zip",
      "uploader": {
        "login": "github-actions[bot]",
        "id": 41898282,
        "node_id": "MDM6Qm90NDE4OTgyODI=",
        "avatar_url": "https://avatars.githubusercontent.com/in/15368?v=4",
        "gravatar_id": "",
        "url": "https://api.github.com/users/github-actions%5Bbot%5D",
        "html_url": "https://github.com/apps/github-actions",
        "followers_url": "https://api.github.com/users/github-actions%5Bbot%5D/followers",
        "following_url": "https://api.github.com/users/github-actions%5Bbot%5D/following{/other_user}",
        "gists_url": "https://api.github.com/users/github-actions%5Bbot%5D/gists{/gist_id}",
        "starred_url": "https://api.github.com/users/github-actions%5Bbot%5D/starred{/owner}{/repo}",
        "subscriptions_url": "https://api.github.com/users/github-actions%5Bbot%5D/subscriptions",
        "organizations_url": "https://api.github.com/users/github-actions%5Bbot%5D/orgs",
        "repos_url": "https://api.github.com/users/github-actions%5Bbot%5D/repos",
        "events_url": "https://api.github.com/users/github-actions%5Bbot%5D/events{/privacy}",
        "received_events_url": "https://api.github.com/users/github-actions%5Bbot%5D/received_events",
        "type": "Bot",
        "user_view_type": "public",
        "site_admin": false
      },
      "content_type": "application/zip",
      "state": "uploaded",
      "size": 104435310,
      "digest": "sha256:bddc923c3cbf1bb0ffd95f4cbe583e871116783e540a94b92fcbcc1f0de8ef08",
      "download_count": 0,
      "created_at": "2026-05-25T07:24:27Z",
      "updated_at": "2026-05-25T07:24:34Z",
      "browser_download_url": "https://github.com/LeoLun/willow/releases/download/v0.0.2/Willow.Work-darwin-arm64-0.0.2.zip"
    },
    {
      "url": "https://api.github.com/repos/LeoLun/willow/releases/assets/429149114",
      "id": 429149114,
      "node_id": "RA_kwDOOgHXD84ZlEu6",
      "name": "Willow.Work-darwin-x64-0.0.2.zip",
      "label": "Willow Work-darwin-x64-0.0.2.zip",
      "uploader": {
        "login": "github-actions[bot]",
        "id": 41898282,
        "node_id": "MDM6Qm90NDE4OTgyODI=",
        "avatar_url": "https://avatars.githubusercontent.com/in/15368?v=4",
        "gravatar_id": "",
        "url": "https://api.github.com/users/github-actions%5Bbot%5D",
        "html_url": "https://github.com/apps/github-actions",
        "followers_url": "https://api.github.com/users/github-actions%5Bbot%5D/followers",
        "following_url": "https://api.github.com/users/github-actions%5Bbot%5D/following{/other_user}",
        "gists_url": "https://api.github.com/users/github-actions%5Bbot%5D/gists{/gist_id}",
        "starred_url": "https://api.github.com/users/github-actions%5Bbot%5D/starred{/owner}{/repo}",
        "subscriptions_url": "https://api.github.com/users/github-actions%5Bbot%5D/subscriptions",
        "organizations_url": "https://api.github.com/users/github-actions%5Bbot%5D/orgs",
        "repos_url": "https://api.github.com/users/github-actions%5Bbot%5D/repos",
        "events_url": "https://api.github.com/users/github-actions%5Bbot%5D/events{/privacy}",
        "received_events_url": "https://api.github.com/users/github-actions%5Bbot%5D/received_events",
        "type": "Bot",
        "user_view_type": "public",
        "site_admin": false
      },
      "content_type": "application/zip",
      "state": "uploaded",
      "size": 115239078,
      "digest": "sha256:636a5a386545d44fe32df3972c93ed50549d9bcd8fc9b3ffe12bb080d4252d6b",
      "download_count": 0,
      "created_at": "2026-05-25T07:24:27Z",
      "updated_at": "2026-05-25T07:24:34Z",
      "browser_download_url": "https://github.com/LeoLun/willow/releases/download/v0.0.2/Willow.Work-darwin-x64-0.0.2.zip"
    }
  ],
  "tarball_url": "https://api.github.com/repos/LeoLun/willow/tarball/v0.0.2",
  "zipball_url": "https://api.github.com/repos/LeoLun/willow/zipball/v0.0.2",
  "body": null
}
